Workbook

Sheet Roadmap QA Automation
A1: ID | B1: Etapa | C1: Tipo de cliente | D1: Nombre de flujo a automatizar | E1: Descripción del flujo a automatizar | F1: Tipo de escenario | G1: Criticidad | H1: Prioridad | I1: Estado de automatización % | J1: Dependencias | K1: Observaciones
A2: QA-AUTO-001 | B2: 01. Compra | C2: B2C Vetify | D2: Compra de plan B2C | E2: Realizar compra de un plan Vetify | F2: Happy Path | G2: Alta | H2: 1 | I2: 50 | K2: Incluye TS-01 a TS-07 de Flujo de Compra (compra exitosa, fallida, asociacion con usuario existente, cupones, formulario pasos 1-3). 19/31 CPs automatizados. Principal freno: TS-04 Cupones (1/7) por falta de un cupon de prueba real en el ambiente de QA -- es un tema de datos/negocio, no de codigo.
A3: QA-AUTO-002 | B3: 01. Compra | C3: OSDE Adquirente | D3: Compra de plan OSDE Adquirente | E3: Realizar compra de un plan Vetify | F3: Happy Path | G3: Alta | H3: 1 | I3: 50 | K3: Incluye TS-01 a TS-07. 16/31 CPs automatizados. Mismo freno de cupon que B2C (TS-04, 1/7). Pendiente de confirmar: TS-01 (compra exitosa) figura 0/8 en Casos de Prueba.xlsx, pero hoy (29/08) hay un test real de compra exitosa para OSDE Adquirente que corre y pasa -- posible desactualizacion del tracker tactico, no de este roadmap.
A4: QA-AUTO-003 | B4: 01. Compra | C4: OSDE Capitado | D4: Alta de plan capitado | E4: Procesar alta de un afiliado capitado OSDE y validar asociación del plan. | F4: Happy Path | G4: Alta | H4: 1 | I4: 100 | K4: 5/5 CPs automatizados (TS-01 Proceso de Compra + TS-02 Validacion de formulario).
A5: QA-AUTO-004 | B5: 01. Compra | C5: Flux Capitado | D5: Alta de plan Flux Capitado | E5: Procesar alta Flux Capitado y validar asociación de cliente, plan y mascota. | F5: Happy Path | G5: Alta | H5: 1 | I5: 100 | K5: 5/5 CPs automatizados, pero la unica cuenta del pool tageada Flux Capitado resulto ser un producto OSDE real bajo la etiqueta equivocada (ver qa-workspace/known-issues.md). El 100% no confirma todavia cobertura del sub-segmento Flux genuino.
A6: QA-AUTO-005 | B6: 02. Backend / Engage/ Sise | C6: B2C Vetify | D6: Alta de cliente | E6: Validar creación del cliente en Engage a partir de una compra B2C. | F6: Happy Path | G6: Alta | H6: 1 | I6: 0 | K6: Gap en el tracker tactico: no existe una hoja de Casos de Prueba.xlsx dedicada a validaciones de backend Salesforce o Engage. Nota importante: el codigo de Flujo de Compra (VetifyCheckoutPage.completePersonalData) SI valida partes del payload enviado a la API de Salesforce como parte del test de compra, pero eso no esta documentado como CP propio -- posible cobertura parcial no trackeada, requiere revision dedicada antes de confirmar un numero distinto de 0.
A7: QA-AUTO-006 | B7: 02. Backend / Engage/ Sise | C7: OSDE Adquirente | D7: Alta de cliente adquirente | E7: Validar creación del cliente adquirente y datos asociados posterior a compra. | F7: Happy Path | G7: Alta | H7: 1 | I7: 0 | K7: Gap en el tracker tactico: no existe una hoja de Casos de Prueba.xlsx dedicada a validaciones de backend Salesforce o Engage. Nota importante: el codigo de Flujo de Compra (VetifyCheckoutPage.completePersonalData) SI valida partes del payload enviado a la API de Salesforce como parte del test de compra, pero eso no esta documentado como CP propio -- posible cobertura parcial no trackeada, requiere revision dedicada antes de confirmar un numero distinto de 0.
A8: QA-AUTO-007 | B8: 02. Backend / Sise | C8: OSDE Capitado | D8: Alta de cliente capitado | E8: Validar alta y asociación del cliente capitado con OSDE y plan correspondiente. | F8: Happy Path | G8: Alta | H8: 1 | I8: 0 | K8: Gap en el tracker tactico: no existe una hoja de Casos de Prueba.xlsx dedicada a validaciones de backend Salesforce o Engage. Nota importante: el codigo de Flujo de Compra (VetifyCheckoutPage.completePersonalData) SI valida partes del payload enviado a la API de Salesforce como parte del test de compra, pero eso no esta documentado como CP propio -- posible cobertura parcial no trackeada, requiere revision dedicada antes de confirmar un numero distinto de 0.
A9: QA-AUTO-008 | B9: 02. Backend / Sise | C9: Flux Capitado | D9: Alta de cliente Flux | E9: Validar alta del cliente y asociación correcta con plan Flux Capitado. | F9: Happy Path | G9: Alta | H9: 1 | I9: 0 | K9: Gap en el tracker tactico: no existe una hoja de Casos de Prueba.xlsx dedicada a validaciones de backend Salesforce o Engage. Nota importante: el codigo de Flujo de Compra (VetifyCheckoutPage.completePersonalData) SI valida partes del payload enviado a la API de Salesforce como parte del test de compra, pero eso no esta documentado como CP propio -- posible cobertura parcial no trackeada, requiere revision dedicada antes de confirmar un numero distinto de 0.
A10: QA-AUTO-009 | B10: 02. Backend / Engage/ Sise | C10: B2C Vetify | D10: Alta | E10: Validar que el cliente comprado quede correctamente generado/habilitado en Engage. | F10: Happy Path | G10: Alta | H10: 1 | I10: 0 | K10: Gap en el tracker tactico: no existe una hoja de Casos de Prueba.xlsx dedicada a validaciones de backend Salesforce o Engage. Nota importante: el codigo de Flujo de Compra (VetifyCheckoutPage.completePersonalData) SI valida partes del payload enviado a la API de Salesforce como parte del test de compra, pero eso no esta documentado como CP propio -- posible cobertura parcial no trackeada, requiere revision dedicada antes de confirmar un numero distinto de 0.
A11: QA-AUTO-010 | B11: 02. Backend / Engage/ Sise | C11: OSDE Adquirente | D11: Alta | E11: Validar generación del cliente adquirente en Engage posterior a la compra. | F11: Happy Path | G11: Alta | H11: 1 | I11: 0 | K11: Gap en el tracker tactico: no existe una hoja de Casos de Prueba.xlsx dedicada a validaciones de backend Salesforce o Engage. Nota importante: el codigo de Flujo de Compra (VetifyCheckoutPage.completePersonalData) SI valida partes del payload enviado a la API de Salesforce como parte del test de compra, pero eso no esta documentado como CP propio -- posible cobertura parcial no trackeada, requiere revision dedicada antes de confirmar un numero distinto de 0.
A12: QA-AUTO-011 | B12: 02. Backend / Sise | C12: OSDE Capitado | D12: Alta - capitado osde | E12: Validar generación/habilitación del cliente capitado | F12: Happy Path | G12: Alta | H12: 1 | I12: 0 | K12: Gap en el tracker tactico: no existe una hoja de Casos de Prueba.xlsx dedicada a validaciones de backend Salesforce o Engage. Nota importante: el codigo de Flujo de Compra (VetifyCheckoutPage.completePersonalData) SI valida partes del payload enviado a la API de Salesforce como parte del test de compra, pero eso no esta documentado como CP propio -- posible cobertura parcial no trackeada, requiere revision dedicada antes de confirmar un numero distinto de 0.
A13: QA-AUTO-012 | B13: 02. Backend / Engage/ Sise | C13: Flux Capitado | D13: Alta en Engage - Flux | E13: Validar generación/habilitación del cliente Flux en Engage. | F13: Happy Path | G13: Alta | H13: 1 | I13: 0 | K13: Gap en el tracker tactico: no existe una hoja de Casos de Prueba.xlsx dedicada a validaciones de backend Salesforce o Engage. Nota importante: el codigo de Flujo de Compra (VetifyCheckoutPage.completePersonalData) SI valida partes del payload enviado a la API de Salesforce como parte del test de compra, pero eso no esta documentado como CP propio -- posible cobertura parcial no trackeada, requiere revision dedicada antes de confirmar un numero distinto de 0.
... A85: QA-AUTO-090 | B85: 10. Reintegros | C85: Todos | D85: Facturas - estado vacio | E85: Validar que se muestra el estado vacio correcto cuando el usuario no tiene facturas cargadas. | F85: Happy Path | G85: Baja | H85: 3 | I85: 100 | K85: Hoja Miscelaneas, CP-09 (Mobile): automatizado. Fila agregada porque no tenia equivalente en el roadmap original -- es un smoke test de estado vacio, no ejercita el flujo real de reintegro.
A86: QA-AUTO-091 | B86: 16. Flujos End-to-End | C86: Todos | D86: Flujo completo: Creacion de usuario, Compra y Reseteo de contrasena | E86: Validar el journey completo del cliente en una sola corrida continua: registrarse, activar la cuenta, comprar un plan y, en otro momento, resetear la contrasena con exito. | F86: Regresion | G86: Alta | H86: 1 | I86: 0 | J86: QA-AUTO-018, QA-AUTO-021, QA-AUTO-001, QA-AUTO-026 | K86: IMPORTANTE: cada paso por separado SI esta automatizado y pasando (Registracion 100%, Activacion 100%, Compra B2C 50%, Reseteo de contrasena 50%), pero NINGUN test encadena las 4 etapas en una sola corrida continua -- son specs independientes con cuentas distintas. El 0% refleja el journey end-to-end tal como lo pidio la PO, no la cobertura de las partes.
A87: QA-AUTO-092 | B87: 16. Flujos End-to-End | C87: Todos | D87: Flujo completo: Compra, Carga de credencial y Solicitud de videollamada | E87: Validar el journey completo desde que el cliente compra un plan hasta que consigue agendar una videollamada, pasando por cargar la credencial de su mascota, en una sola corrida continua. | F87: Regresion | G87: Alta | H87: 1 | I87: 0 | J87: QA-AUTO-001, QA-AUTO-039, QA-AUTO-048 | K87: Mismo caso que la fila anterior: las 3 partes estan automatizadas por separado (Compra 50%, Carga de credencial 100%, Solicitar videollamada 100%) pero nunca encadenadas en un solo test end-to-end. Candidato natural a automatizar primero entre los 2 journeys nuevos, porque sus 3 partes ya estan en mejor estado individualmente.
A88: QA-AUTO-093 | B88: 11. Vetify Plus | C88: Todos | D88: Banner Cooper en Home | E88: Validar que el banner de Cooper se muestra en Home para los 3 segmentos (Vetify B2C, OSDE Capitado, OSDE Adquirente). | F88: Happy Path | G88: Alta | H88: 1 | I88: 100 | K88: IMAS-4356/IMAS-4435. tests/projects/vetify-webapp/navigation.spec.ts TS-05, 3 casos, verificado Desktop y Mobile (Android).
A89: QA-AUTO-094 | B89: 11. Vetify Plus | C89: Todos | D89: Menu Beneficios - segmentacion Cooper/Vetify PLUS | E89: Validar que el menu lateral (seccion Beneficios) muestra Cooper y Vetify PLUS para B2C, y solo Cooper para OSDE Capitado. | F89: Happy Path | G89: Alta | H89: 1 | I89: 100 | K89: IMAS-4356/IMAS-4435. TS-04 TC-01/02/03, verificado Desktop y Mobile. OSDE Adquirente no automatizado a proposito: la segmentacion real depende del policyId (producto real) de la cuenta, no del segmento -- ver docs/conocimiento-sistema.md.

Sheet Dashboard Ejecutivo
B2: QA AUTOMATION | VETIFY
B5: Resumen ejecutivo
B7: Total escenarios | E7: % automatizado total | H7: Escenarios 100%
B8: =COUNTA('Roadmap QA Automation'!A2:A1998) -> 88 | E8: =IFERROR(AVERAGE('Roadmap QA Automation'!I2:I1998)/100,0) -> 0.40340909 | H8: =COUNTIF('Roadmap QA Automation'!I2:I1998,100) -> 32
B12: Automatización por etapa
B13: Etapa | C13: Escenarios | D13: % automatizado
B14: 01. Compra | C14: =COUNTIF('Roadmap QA Automation'!B:B,LEFT(B14,3)&"*") -> 4 | D14: =IFERROR(AVERAGEIF('Roadmap QA Automation'!B:B,LEFT(B14,3)&"*",'Roadmap QA Automation'!I:I)/100,0) -> 0.75
B15: 02. Backend / Salesforce / Engage | C15: =COUNTIF('Roadmap QA Automation'!B:B,LEFT(B15,3)&"*") -> 10 | D15: =IFERROR(AVERAGEIF('Roadmap QA Automation'!B:B,LEFT(B15,3)&"*",'Roadmap QA Automation'!I:I)/100,0) -> 0
B16: 03. Usuario / Acceso | C16: =COUNTIF('Roadmap QA Automation'!B:B,LEFT(B16,3)&"*") -> 19 | D16: =IFERROR(AVERAGEIF('Roadmap QA Automation'!B:B,LEFT(B16,3)&"*",'Roadmap QA Automation'!I:I)/100,0) -> 0.60526316
B17: 04. WebApp - Perfil y mascotas | C17: =COUNTIF('Roadmap QA Automation'!B:B,LEFT(B17,3)&"*") -> 5 | D17: =IFERROR(AVERAGEIF('Roadmap QA Automation'!B:B,LEFT(B17,3)&"*",'Roadmap QA Automation'!I:I)/100,0) -> 0.4
B18: 05. Credencial | C18: =COUNTIF('Roadmap QA Automation'!B:B,LEFT(B18,3)&"*") -> 5 | D18: =IFERROR(AVERAGEIF('Roadmap QA Automation'!B:B,LEFT(B18,3)&"*",'Roadmap QA Automation'!I:I)/100,0) -> 0.7
B19: 06. Servicios | C19: =COUNTIF('Roadmap QA Automation'!B:B,LEFT(B19,3)&"*") -> 5 | D19: =IFERROR(AVERAGEIF('Roadmap QA Automation'!B:B,LEFT(B19,3)&"*",'Roadmap QA Automation'!I:I)/100,0) -> 1
B20: 07. Videollamada | C20: =COUNTIF('Roadmap QA Automation'!B:B,LEFT(B20,3)&"*") -> 7 | D20: =IFERROR(AVERAGEIF('Roadmap QA Automation'!B:B,LEFT(B20,3)&"*",'Roadmap QA Automation'!I:I)/100,0) -> 0.42857143
B21: 08. Prestadores / Red | C21: =COUNTIF('Roadmap QA Automation'!B:B,LEFT(B21,3)&"*") -> 5 | D21: =IFERROR(AVERAGEIF('Roadmap QA Automation'!B:B,LEFT(B21,3)&"*",'Roadmap QA Automation'!I:I)/100,0) -> 0
B22: 09. Cobertura y condicionados | C22: =COUNTIF('Roadmap QA Automation'!B:B,LEFT(B22,3)&"*") -> 4 | D22: =IFERROR(AVERAGEIF('Roadmap QA Automation'!B:B,LEFT(B22,3)&"*",'Roadmap QA Automation'!I:I)/100,0) -> 0.0625
B23: 10. Reintegros | C23: =COUNTIF('Roadmap QA Automation'!B:B,LEFT(B23,3)&"*") -> 7 | D23: =IFERROR(AVERAGEIF('Roadmap QA Automation'!B:B,LEFT(B23,3)&"*",'Roadmap QA Automation'!I:I)/100,0) -> 0.17857143
B24: 11. Vetify Plus / Planes | C24: =COUNTIF('Roadmap QA Automation'!B:B,LEFT(B24,3)&"*") -> 6 | D24: =IFERROR(AVERAGEIF('Roadmap QA Automation'!B:B,LEFT(B24,3)&"*",'Roadmap QA Automation'!I:I)/100,0) -> 0.66666667
B25: 12. Notificaciones | C25: =COUNTIF('Roadmap QA Automation'!B:B,LEFT(B25,3)&"*") -> 0 | D25: =IFERROR(AVERAGEIF('Roadmap QA Automation'!B:B,LEFT(B25,3)&"*",'Roadmap QA Automation'!I:I)/100,0) -> 0
... B29: 16. Flujos End-to-End | C29: =COUNTIF('Roadmap QA Automation'!B:B,LEFT(B29,3)&"*") -> 2 | D29: =IFERROR(AVERAGEIF('Roadmap QA Automation'!B:B,LEFT(B29,3)&"*",'Roadmap QA Automation'!I:I)/100,0) -> 0
B30: Estado de automatización
B31: Estado | C31: Cantidad
B32: 0% | C32: =COUNTIF('Roadmap QA Automation'!I:I,0) -> 48
B33: 25% | C33: =COUNTIF('Roadmap QA Automation'!I:I,25) -> 3
B34: 50% | C34: =COUNTIF('Roadmap QA Automation'!I:I,50) -> 4
B35: 75% | C35: =COUNTIF('Roadmap QA Automation'!I:I,75) -> 1
B36: 100% | C36: =COUNTIF('Roadmap QA Automation'!I:I,100) -> 32
B40: Automatización por criticidad
B41: Criticidad | C41: Escenarios | D41: % automatizado
B42: Alta | C42: =COUNTIF('Roadmap QA Automation'!G:G,B42) -> 65 | D42: =IFERROR(AVERAGEIF('Roadmap QA Automation'!G:G,B42,'Roadmap QA Automation'!I:I)/100,0) -> 0.39615385
B43: Media | C43: =COUNTIF('Roadmap QA Automation'!G:G,B43) -> 19 | D43: =IFERROR(AVERAGEIF('Roadmap QA Automation'!G:G,B43,'Roadmap QA Automation'!I:I)/100,0) -> 0.46052632
B44: Baja | C44: =COUNTIF('Roadmap QA Automation'!G:G,B44) -> 4 | D44: =IFERROR(AVERAGEIF('Roadmap QA Automation'!G:G,B44,'Roadmap QA Automation'!I:I)/100,0) -> 0.25
B47: Automatización por canal
B48: Canal | C48: Escenarios | D48: % automatizado
B49: B2C Vetify | C49: =COUNTIF('Roadmap QA Automation'!C:C,B49) -> 3 | D49: =IFERROR(AVERAGEIF('Roadmap QA Automation'!C:C,B49,'Roadmap QA Automation'!I:I)/100,0) -> 0.16666667
B50: OSDE Adquirente | C50: =COUNTIF('Roadmap QA Automation'!C:C,B50) -> 3 | D50: =IFERROR(AVERAGEIF('Roadmap QA Automation'!C:C,B50,'Roadmap QA Automation'!I:I)/100,0) -> 0.16666667
B51: OSDE Capitado | C51: =COUNTIF('Roadmap QA Automation'!C:C,B51) -> 3 | D51: =IFERROR(AVERAGEIF('Roadmap QA Automation'!C:C,B51,'Roadmap QA Automation'!I:I)/100,0) -> 0.33333333
B52: Flux Capitado | C52: =COUNTIF('Roadmap QA Automation'!C:C,B52) -> 3 | D52: =IFERROR(AVERAGEIF('Roadmap QA Automation'!C:C,B52,'Roadmap QA Automation'!I:I)/100,0) -> 0.33333333
B53: Todos | C53: =COUNTIF('Roadmap QA Automation'!C:C,B53) -> 70 | D53: =IFERROR(AVERAGEIF('Roadmap QA Automation'!C:C,B53,'Roadmap QA Automation'!I:I)/100,0) -> 0.40714286

Sheet Guía
B2: GUÍA DE USO
B4: Objetivo | C4: Roadmap editable de escenarios críticos de QA Automation para Vetify, ordenado end-to-end desde compra/alta hasta navegación y servicios.
B6: Escala de automatización
B7: 0% | C7: No iniciado
B8: 25% | C8: Escenario definido / preparación
B9: 50% | C9: Automatización en desarrollo
B10: 75% | C10: Automatizado, pendiente de estabilización
B11: 100% | C11: Automatizado y estable
B13: Criticidad
B14: Alta | C14: Impacta venta, alta, acceso o servicio principal / impacto económico
B15: Media | C15: Funcionalidad importante con workaround o impacto acotado
B16: Baja | C16: Funcionalidad secundaria/informativa o de bajo impacto
B18: Regla del dashboard | C18: El dashboard toma los porcentajes de la hoja Roadmap QA Automation. Actualizá la columna Estado de automatización % y Excel recalcula los indicadores.
